fish_audio_sdk-2025.4.2.dist-info/METADATA
fish_audio_sdk-2025.4.2.dist-info/WHEEL
fish_audio_sdk-2025.4.2.dist-info/entry_points.txt
fish_audio_sdk/__init__.py
fish_audio_sdk/apis.py
fish_audio_sdk/exceptions.py
fish_audio_sdk/io.py
fish_audio_sdk/schemas.py
fish_audio_sdk/websocket.py
fish_audio_sdk-2025.4.2.dist-info/RECORD
