Metadata-Version: 2.1
Name: fish-audio-sdk
Version: 2025.4.2
Summary: fish.audio platform api sdk
Author-Email: abersheeran <me@abersheeran.com>
License: MIT
Requires-Python: >=3.10
Requires-Dist: httpx>=0.27.2
Requires-Dist: ormsgpack>=1.5.0
Requires-Dist: pydantic>=2.9.1
Requires-Dist: httpx-ws>=0.6.2
